mcplib/__init__.py
mcplib/main.py
mcplib-0.1.0.dist-info/METADATA
mcplib-0.1.0.dist-info/WHEEL
mcplib-0.1.0.dist-info/top_level.txt
mcplib-0.1.0.dist-info/RECORD
